pure_cifar_10/__init__.py
pure_cifar_10/loader.py
pure_cifar_10-0.1.1.dist-info/METADATA
pure_cifar_10-0.1.1.dist-info/WHEEL
pure_cifar_10-0.1.1.dist-info/top_level.txt
pure_cifar_10-0.1.1.dist-info/RECORD
