Metadata-Version: 2.4
Name: pure_cifar_10
Version: 0.1.1
Summary: Pure Python/NumPy CIFAR-10 dataset loader
Home-page: https://github.com/ratulb/pure_cifar_10
Author: Ratul Buragohain
Author-email: ratul75@hotmail.com
Classifier: Programming Language :: Python :: 3
Classifier: License :: OSI Approved :: MIT License
Classifier: Operating System :: OS Independent
Requires-Python: >=3.10
Requires-Dist: numpy>=2.0.0
Requires-Dist: tqdm>=4.66.0
Dynamic: author
Dynamic: author-email
Dynamic: classifier
Dynamic: description
Dynamic: description-content-type
Dynamic: home-page
Dynamic: requires-dist
Dynamic: requires-python
Dynamic: summary
